Metadata-Version: 1.0
Name: Rpi-encoder
Version: 0.1.3
Summary: High-level interface for the KY040 rotary encoder and switch.
Home-page: https://github.com/Akex2/Rpi_Encoder
Author: Alex
Author-email: schoints@gmail.com
License: UNKNOWN
Keywords: keyes rotary encoder switch A B
Platform: UNKNOWN
